grader/__init__.py
redkyn_grader-0.1.0.data/data/share/grader/_grader.zsh
redkyn_grader-0.1.0.dist-info/METADATA
redkyn_grader-0.1.0.dist-info/WHEEL
redkyn_grader-0.1.0.dist-info/entry_points.txt
redkyn_grader-0.1.0.dist-info/top_level.txt
redkyn_grader-0.1.0.dist-info/RECORD
