Metadata-Version: 2.1
Name: redkyn-grader
Version: 0.1.0
Summary: A grading framework for evaluating programming assignments
Home-page: https://github.com/redkyn/grader
Author: B. Rhoades, N. Jarus, M. Wisely, & T. Morrow
Author-email: jarus@mst.edu
License: UNKNOWN
Platform: UNKNOWN
Classifier: Development Status :: 4 - Beta
Classifier: Intended Audience :: Education
Classifier: Topic :: Education
Classifier: Topic :: Software Development :: Version Control :: Git
Classifier: Environment :: Console
Classifier: License :: OSI Approved :: MIT License
Classifier: Programming Language :: Python :: 3
Classifier: Programming Language :: Python :: 3 :: Only
Classifier: Programming Language :: Python :: 3.4
Classifier: Programming Language :: Python :: 3.5
Classifier: Programming Language :: Python :: 3.6
Classifier: Programming Language :: Python :: 3.7
Requires-Python: >=3.4
Requires-Dist: setuptools
Requires-Dist: GitPython (>=2.1.8)
Requires-Dist: docker (>=3.6.0)
Requires-Dist: PyYAML (>=3.13)
Requires-Dist: jsonschema (>=2.5.1)
Requires-Dist: PTable (==0.9.2)
Requires-Dist: colorlog (<3,>=2.6)
Requires-Dist: Jinja2 (>=2.10)
Requires-Dist: redkyn-common (>=1.0.1)
